here/__init__.py
here/main.py
here_log-1.0.1.dist-info/LICENSE
here_log-1.0.1.dist-info/METADATA
here_log-1.0.1.dist-info/WHEEL
here_log-1.0.1.dist-info/top_level.txt
here_log-1.0.1.dist-info/RECORD
